gimmegit/__init__.py
gimmegit/_args.py
gimmegit/_cli.py
gimmegit/_help.py
gimmegit/_inspect.py
gimmegit/_remote.py
gimmegit/_status.py
gimmegit/_version.py
gimmegit-0.4.0.dist-info/licenses/LICENSE
gimmegit-0.4.0.dist-info/WHEEL
gimmegit-0.4.0.dist-info/entry_points.txt
gimmegit-0.4.0.dist-info/METADATA
gimmegit-0.4.0.dist-info/RECORD
