Metadata-Version: 2.4
Name: gimmegit
Version: 0.4.0
Summary: A tool for cloning GitHub repos and creating branches.
Author: Dave Wilding
Author-email: Dave Wilding <tech@dpw.me>
License-Expression: MIT
License-File: LICENSE
Requires-Dist: gitpython>=3.1,<4
Requires-Dist: pre-commit>=4.4,<5
Requires-Dist: pygithub>=2.6,<3
Requires-Python: >=3.11
